{
    "characters": {
        "n": 76,
        "female": {
            "n": 10,
            "p": 0.13
        },
        "male": {
            "n": 18,
            "p": 0.24
        },
        "group/nonbinary": {
            "n": 3,
            "p": 0.04
        },
        "unknown": {
            "n": 45,
            "p": 0.59
        },
        "primary": {
            "n": 3,
            "p": 0.04
        },
        "secondary": {
            "n": 0,
            "p": 0
        },
        "tertiary": {
            "n": 73,
            "p": 0.96
        },
        "female_primary": {
            "n": 2,
            "p": 0.03
        },
        "female_secondary": {
            "n": 0,
            "p": 0
        },
        "female_tertiary": {
            "n": 8,
            "p": 0.11
        },
        "male_primary": {
            "n": 1,
            "p": 0.01
        },
        "male_secondary": {
            "n": 0,
            "p": 0
        },
        "male_tertiary": {
            "n": 17,
            "p": 0.22
        },
        "group/nonbinary_primary": {
            "n": 0,
            "p": 0.0
        },
        "group/nonbinary_secondary": {
            "n": 0,
            "p": 0
        },
        "group/nonbinary_tertiary": {
            "n": 3,
            "p": 0.04
        },
        "unknown_primary": {
            "n": 0,
            "p": 0.0
        },
        "unknown_secondary": {
            "n": 0,
            "p": 0
        },
        "unknown_tertiary": {
            "n": 45,
            "p": 0.59
        },
        "appearances": {
            "all": [
                66,
                52,
                44,
                19,
                12,
                11,
                7,
                7,
                7,
                7,
                6,
                6,
                6,
                5,
                4,
                3,
                3,
                3,
                3,
                2,
                2,
                2,
                1,
                1,
                1,
                1,
                1,
                1,
                1,
                1,
                1,
                1,
                1,
                1,
                1,
                1,
                1,
                1,
                1,
                1,
                1,
                1,
                1,
                1,
                1,
                1,
                1,
                1,
                1,
                1,
                1,
                1,
                1,
                1,
                1,
                1,
                1,
                1,
                1,
                1,
                1,
                1,
                1,
                1,
                1,
                1,
                1,
                1,
                1,
                1,
                1,
                1,
                1,
                1,
                1,
                1
            ],
            "female": [
                52,
                44,
                12,
                5,
                3,
                3,
                2,
                1,
                1,
                1
            ],
            "male": [
                66,
                19,
                11,
                7,
                7,
                7,
                6,
                6,
                4,
                1,
                1,
                1,
                1,
                1,
                1,
                1,
                1,
                1
            ],
            "group/nonbinary": [
                6,
                3,
                2
            ],
            "unknown": [
                7,
                3,
                2,
                1,
                1,
                1,
                1,
                1,
                1,
                1,
                1,
                1,
                1,
                1,
                1,
                1,
                1,
                1,
                1,
                1,
                1,
                1,
                1,
                1,
                1,
                1,
                1,
                1,
                1,
                1,
                1,
                1,
                1,
                1,
                1,
                1,
                1,
                1,
                1,
                1,
                1,
                1,
                1,
                1,
                1
            ]
        }
    },
    "events": {
        "counts": [
            {
                "gender": "female",
                "importance": "primary",
                "direct_object": 43,
                "subject": 64,
                "total": 107
            },
            {
                "gender": "female",
                "importance": "tertiary",
                "direct_object": 9,
                "subject": 34,
                "total": 43
            },
            {
                "gender": "female",
                "importance": "total",
                "direct_object": 52,
                "subject": 98,
                "total": 150
            },
            {
                "gender": "group/nonbinary",
                "importance": "tertiary",
                "direct_object": 7,
                "subject": 8,
                "total": 15
            },
            {
                "gender": "group/nonbinary",
                "importance": "total",
                "direct_object": 7,
                "subject": 8,
                "total": 15
            },
            {
                "gender": "male",
                "importance": "primary",
                "direct_object": 33,
                "subject": 39,
                "total": 72
            },
            {
                "gender": "male",
                "importance": "tertiary",
                "direct_object": 39,
                "subject": 46,
                "total": 85
            },
            {
                "gender": "male",
                "importance": "total",
                "direct_object": 72,
                "subject": 85,
                "total": 157
            },
            {
                "gender": "total",
                "importance": "",
                "direct_object": 153,
                "subject": 211,
                "total": 364
            },
            {
                "gender": "unknown",
                "importance": "tertiary",
                "direct_object": 22,
                "subject": 20,
                "total": 42
            },
            {
                "gender": "unknown",
                "importance": "total",
                "direct_object": 22,
                "subject": 20,
                "total": 42
            }
        ],
        "top_events": {
            "female": [
                {
                    "event_lemma": "play",
                    "argument": "subject",
                    "female_male_odds": 16.67
                },
                {
                    "event_lemma": "come",
                    "argument": "subject",
                    "female_male_odds": 10.0
                },
                {
                    "event_lemma": "eat",
                    "argument": "direct_object",
                    "female_male_odds": 7.14
                },
                {
                    "event_lemma": "go",
                    "argument": "subject",
                    "female_male_odds": 4.35
                },
                {
                    "event_lemma": "open",
                    "argument": "subject",
                    "female_male_odds": 4.35
                },
                {
                    "event_lemma": "recite",
                    "argument": "subject",
                    "female_male_odds": 4.35
                },
                {
                    "event_lemma": "sign",
                    "argument": "subject",
                    "female_male_odds": 4.35
                },
                {
                    "event_lemma": "do",
                    "argument": "subject",
                    "female_male_odds": 4.35
                },
                {
                    "event_lemma": "dance",
                    "argument": "subject",
                    "female_male_odds": 4.35
                },
                {
                    "event_lemma": "think",
                    "argument": "direct_object",
                    "female_male_odds": 2.38
                }
            ],
            "male": [
                {
                    "event_lemma": "put",
                    "male_female_odds": 6.87,
                    "argument": "direct_object"
                },
                {
                    "event_lemma": "put",
                    "male_female_odds": 5.91,
                    "argument": "subject"
                },
                {
                    "event_lemma": "felt",
                    "male_female_odds": 5.26,
                    "argument": "direct_object"
                },
                {
                    "event_lemma": "control",
                    "male_female_odds": 5.26,
                    "argument": "direct_object"
                },
                {
                    "event_lemma": "come",
                    "male_female_odds": 3.71,
                    "argument": "direct_object"
                },
                {
                    "event_lemma": "introduce",
                    "male_female_odds": 3.71,
                    "argument": "direct_object"
                },
                {
                    "event_lemma": "remember",
                    "male_female_odds": 3.71,
                    "argument": "direct_object"
                },
                {
                    "event_lemma": "seize",
                    "male_female_odds": 3.71,
                    "argument": "direct_object"
                },
                {
                    "event_lemma": "carry",
                    "male_female_odds": 3.71,
                    "argument": "direct_object"
                },
                {
                    "event_lemma": "eat",
                    "male_female_odds": 2.76,
                    "argument": "subject"
                },
                {
                    "event_lemma": "sing",
                    "male_female_odds": 2.64,
                    "argument": "subject"
                },
                {
                    "event_lemma": "see",
                    "male_female_odds": 2.14,
                    "argument": "subject"
                }
            ],
            "unbiased": [
                {
                    "event_lemma": "know",
                    "male_female_odds": 1.95,
                    "argument": "subject"
                },
                {
                    "event_lemma": "begin",
                    "male_female_odds": 1.95,
                    "argument": "subject"
                },
                {
                    "event_lemma": "felt",
                    "male_female_odds": 1.95,
                    "argument": "subject"
                },
                {
                    "event_lemma": "kick",
                    "male_female_odds": 1.95,
                    "argument": "subject"
                },
                {
                    "event_lemma": "place",
                    "male_female_odds": 1.95,
                    "argument": "subject"
                },
                {
                    "event_lemma": "pay",
                    "male_female_odds": 1.95,
                    "argument": "subject"
                },
                {
                    "event_lemma": "know",
                    "male_female_odds": 1.72,
                    "argument": "direct_object"
                },
                {
                    "event_lemma": "take",
                    "male_female_odds": 1.21,
                    "argument": "direct_object"
                },
                {
                    "event_lemma": "say",
                    "male_female_odds": 1.16,
                    "argument": "subject"
                },
                {
                    "event_lemma": "say",
                    "male_female_odds": 0.71,
                    "argument": "direct_object"
                },
                {
                    "event_lemma": "have",
                    "male_female_odds": 0.69,
                    "argument": "subject"
                },
                {
                    "event_lemma": "cry",
                    "male_female_odds": 0.69,
                    "argument": "subject"
                },
                {
                    "event_lemma": "hear",
                    "male_female_odds": 0.69,
                    "argument": "subject"
                }
            ]
        }
    }
}