{
    "characters": {
        "n": 64,
        "female": {
            "n": 11,
            "p": 0.17
        },
        "male": {
            "n": 25,
            "p": 0.39
        },
        "group/nonbinary": {
            "n": 2,
            "p": 0.03
        },
        "unknown": {
            "n": 26,
            "p": 0.41
        },
        "primary": {
            "n": 1,
            "p": 0.02
        },
        "secondary": {
            "n": 2,
            "p": 0.03
        },
        "tertiary": {
            "n": 61,
            "p": 0.95
        },
        "female_primary": {
            "n": 0,
            "p": 0.0
        },
        "female_secondary": {
            "n": 0,
            "p": 0.0
        },
        "female_tertiary": {
            "n": 11,
            "p": 0.17
        },
        "male_primary": {
            "n": 1,
            "p": 0.02
        },
        "male_secondary": {
            "n": 2,
            "p": 0.03
        },
        "male_tertiary": {
            "n": 22,
            "p": 0.34
        },
        "group/nonbinary_primary": {
            "n": 0,
            "p": 0.0
        },
        "group/nonbinary_secondary": {
            "n": 0,
            "p": 0.0
        },
        "group/nonbinary_tertiary": {
            "n": 2,
            "p": 0.03
        },
        "unknown_primary": {
            "n": 0,
            "p": 0.0
        },
        "unknown_secondary": {
            "n": 0,
            "p": 0.0
        },
        "unknown_tertiary": {
            "n": 26,
            "p": 0.41
        },
        "appearances": {
            "all": [
                66,
                26,
                21,
                16,
                16,
                11,
                7,
                7,
                7,
                7,
                6,
                5,
                5,
                5,
                4,
                4,
                3,
                3,
                3,
                3,
                2,
                2,
                2,
                2,
                2,
                1,
                1,
                1,
                1,
                1,
                1,
                1,
                1,
                1,
                1,
                1,
                1,
                1,
                1,
                1,
                1,
                1,
                1,
                1,
                1,
                1,
                1,
                1,
                1,
                1,
                1,
                1,
                1,
                1,
                1,
                1,
                1,
                1,
                1,
                1,
                1,
                1,
                1,
                1
            ],
            "female": [
                16,
                7,
                7,
                5,
                4,
                3,
                3,
                1,
                1,
                1,
                1
            ],
            "male": [
                66,
                26,
                21,
                16,
                11,
                7,
                7,
                6,
                5,
                5,
                4,
                3,
                3,
                2,
                2,
                1,
                1,
                1,
                1,
                1,
                1,
                1,
                1,
                1,
                1
            ],
            "group/nonbinary": [
                2,
                2
            ],
            "unknown": [
                2,
                1,
                1,
                1,
                1,
                1,
                1,
                1,
                1,
                1,
                1,
                1,
                1,
                1,
                1,
                1,
                1,
                1,
                1,
                1,
                1,
                1,
                1,
                1,
                1,
                1
            ]
        }
    },
    "events": {
        "counts": [
            {
                "gender": "female",
                "importance": "tertiary",
                "direct_object": 22,
                "subject": 36,
                "total": 58
            },
            {
                "gender": "female",
                "importance": "total",
                "direct_object": 22,
                "subject": 36,
                "total": 58
            },
            {
                "gender": "group/nonbinary",
                "importance": "tertiary",
                "direct_object": 1,
                "subject": 2,
                "total": 3
            },
            {
                "gender": "group/nonbinary",
                "importance": "total",
                "direct_object": 1,
                "subject": 2,
                "total": 3
            },
            {
                "gender": "male",
                "importance": "primary",
                "direct_object": 24,
                "subject": 50,
                "total": 74
            },
            {
                "gender": "male",
                "importance": "secondary",
                "direct_object": 31,
                "subject": 19,
                "total": 50
            },
            {
                "gender": "male",
                "importance": "tertiary",
                "direct_object": 47,
                "subject": 40,
                "total": 87
            },
            {
                "gender": "male",
                "importance": "total",
                "direct_object": 102,
                "subject": 109,
                "total": 211
            },
            {
                "gender": "total",
                "importance": "",
                "direct_object": 141,
                "subject": 164,
                "total": 305
            },
            {
                "gender": "unknown",
                "importance": "tertiary",
                "direct_object": 16,
                "subject": 17,
                "total": 33
            },
            {
                "gender": "unknown",
                "importance": "total",
                "direct_object": 16,
                "subject": 17,
                "total": 33
            }
        ],
        "top_events": {
            "female": [
                {
                    "event_lemma": "do",
                    "argument": "subject",
                    "female_male_odds": 25.0
                },
                {
                    "event_lemma": "encourage",
                    "argument": "direct_object",
                    "female_male_odds": 8.33
                },
                {
                    "event_lemma": "ride",
                    "argument": "subject",
                    "female_male_odds": 5.26
                },
                {
                    "event_lemma": "make",
                    "argument": "subject",
                    "female_male_odds": 4.55
                },
                {
                    "event_lemma": "lead",
                    "argument": "direct_object",
                    "female_male_odds": 2.94
                },
                {
                    "event_lemma": "tell",
                    "argument": "direct_object",
                    "female_male_odds": 2.27
                },
                {
                    "event_lemma": "think",
                    "argument": "direct_object",
                    "female_male_odds": 2.04
                },
                {
                    "event_lemma": "ask",
                    "argument": "direct_object",
                    "female_male_odds": 2.04
                }
            ],
            "male": [
                {
                    "event_lemma": "take",
                    "male_female_odds": 4.5,
                    "argument": "subject"
                },
                {
                    "event_lemma": "marry",
                    "male_female_odds": 3.77,
                    "argument": "subject"
                },
                {
                    "event_lemma": "visit",
                    "male_female_odds": 2.36,
                    "argument": "subject"
                }
            ],
            "unbiased": [
                {
                    "event_lemma": "invite",
                    "male_female_odds": 1.98,
                    "argument": "direct_object"
                },
                {
                    "event_lemma": "mention",
                    "male_female_odds": 1.98,
                    "argument": "direct_object"
                },
                {
                    "event_lemma": "throw",
                    "male_female_odds": 1.67,
                    "argument": "subject"
                },
                {
                    "event_lemma": "think",
                    "male_female_odds": 1.67,
                    "argument": "subject"
                },
                {
                    "event_lemma": "refuse",
                    "male_female_odds": 1.67,
                    "argument": "subject"
                },
                {
                    "event_lemma": "prepare",
                    "male_female_odds": 1.67,
                    "argument": "subject"
                },
                {
                    "event_lemma": "name",
                    "male_female_odds": 1.67,
                    "argument": "subject"
                },
                {
                    "event_lemma": "mention",
                    "male_female_odds": 1.67,
                    "argument": "subject"
                },
                {
                    "event_lemma": "invite",
                    "male_female_odds": 1.67,
                    "argument": "subject"
                },
                {
                    "event_lemma": "inquire",
                    "male_female_odds": 1.67,
                    "argument": "subject"
                },
                {
                    "event_lemma": "go",
                    "male_female_odds": 1.67,
                    "argument": "subject"
                },
                {
                    "event_lemma": "condescend",
                    "male_female_odds": 1.67,
                    "argument": "subject"
                },
                {
                    "event_lemma": "greet",
                    "male_female_odds": 1.53,
                    "argument": "direct_object"
                },
                {
                    "event_lemma": "decide",
                    "male_female_odds": 1.53,
                    "argument": "direct_object"
                },
                {
                    "event_lemma": "take",
                    "male_female_odds": 1.53,
                    "argument": "direct_object"
                },
                {
                    "event_lemma": "meet",
                    "male_female_odds": 1.53,
                    "argument": "direct_object"
                },
                {
                    "event_lemma": "order",
                    "male_female_odds": 1.53,
                    "argument": "direct_object"
                },
                {
                    "event_lemma": "inquire",
                    "male_female_odds": 1.08,
                    "argument": "direct_object"
                },
                {
                    "event_lemma": "commission",
                    "male_female_odds": 1.08,
                    "argument": "direct_object"
                },
                {
                    "event_lemma": "answer",
                    "male_female_odds": 1.08,
                    "argument": "direct_object"
                },
                {
                    "event_lemma": "intend",
                    "male_female_odds": 1.08,
                    "argument": "direct_object"
                },
                {
                    "event_lemma": "recommend",
                    "male_female_odds": 1.08,
                    "argument": "direct_object"
                },
                {
                    "event_lemma": "visit",
                    "male_female_odds": 1.08,
                    "argument": "direct_object"
                },
                {
                    "event_lemma": "come",
                    "male_female_odds": 0.99,
                    "argument": "subject"
                },
                {
                    "event_lemma": "wish",
                    "male_female_odds": 0.76,
                    "argument": "subject"
                },
                {
                    "event_lemma": "know",
                    "male_female_odds": 0.76,
                    "argument": "subject"
                },
                {
                    "event_lemma": "give",
                    "male_female_odds": 0.71,
                    "argument": "direct_object"
                },
                {
                    "event_lemma": "give",
                    "male_female_odds": 0.71,
                    "argument": "subject"
                },
                {
                    "event_lemma": "say",
                    "male_female_odds": 0.67,
                    "argument": "direct_object"
                },
                {
                    "event_lemma": "know",
                    "male_female_odds": 0.63,
                    "argument": "direct_object"
                },
                {
                    "event_lemma": "say",
                    "male_female_odds": 0.59,
                    "argument": "subject"
                },
                {
                    "event_lemma": "hear",
                    "male_female_odds": 0.54,
                    "argument": "subject"
                },
                {
                    "event_lemma": "ask",
                    "male_female_odds": 0.54,
                    "argument": "subject"
                },
                {
                    "event_lemma": "have",
                    "male_female_odds": 0.54,
                    "argument": "subject"
                }
            ]
        }
    }
}